scadaUtils/Conf_generator.py
scadaUtils/GAIA.py
scadaUtils/Simulators.py
scadaUtils/VersionsManager.py
scadaUtils/__init__.py
scadaUtils/comUtils.py
scadaUtils/dashboard.py
scadaUtils/monitoring.py
scadaUtils/old_minutely_hourly.py
scadaUtils/physics.py
scadaUtils/utils.py
scadaUtils/conf/colormaps.pkl
scadaUtils/conf/data_values.ods
scadaUtils/conf/logo_sylfen.png
scadaUtils/conf/palettes.pkl
scadaUtils/conf/parameters.default.conf
scadaUtils/conf/parameters_RT.default.conf
scadaUtils/conf/units.csv
scadaUtils/static/lib/acolorpicker.js
scadaUtils/static/lib/daterangepicker.css
scadaUtils/static/lib/log_versions.md
scadaUtils/static/lib/search.png
scadaUtils/static/lib/search2.png
scadaUtils/static/lib/sylfen.png
scadaUtils/static/lib/sylfen_logo.ico
scadaUtils/static/lib/css/dropdown_filter.css
scadaUtils/static/lib/css/styles.css
scadaUtils/static/lib/css/toggle_switch.css
scadaUtils/static/lib/js/dashboard.js
scadaUtils/static/lib/js/daterangepicker.js
scadaUtils/static/lib/js/jquery.min.js
scadaUtils/static/lib/js/lib.js
scadaUtils/static/lib/js/local_dash.js
scadaUtils/static/lib/js/mathjax.min.js
scadaUtils/static/lib/js/mathjax_local.js
scadaUtils/static/lib/js/moment.min.js
scadaUtils/static/lib/js/plotly.js
scadaUtils/static/lib/js/showdown.min.js
scadaUtils/static/lib/pictures/angrypainter.gif
scadaUtils/static/lib/pictures/logo_sylfen.png
scadaUtils/static/lib/pictures/peintrepalette.jpeg
scadaUtils/templates/bootstrap_dash.html
scadaUtils/templates/dashboard.html
scadaUtils-0.2.1.dist-info/METADATA
scadaUtils-0.2.1.dist-info/WHEEL
scadaUtils-0.2.1.dist-info/top_level.txt
scadaUtils-0.2.1.dist-info/RECORD
